gl_client-0.3.4.dist-info/METADATA
gl_client-0.3.4.dist-info/WHEEL
glclient/__init__.py
glclient/__pycache__/__init__.cpython-310.pyc
glclient/__pycache__/__init__.cpython-312.pyc
glclient/__pycache__/greenlight_pb2.cpython-310.pyc
glclient/__pycache__/greenlight_pb2.cpython-312.pyc
glclient/__pycache__/greenlight_pb2_grpc.cpython-310.pyc
glclient/__pycache__/greenlight_pb2_grpc.cpython-312.pyc
glclient/__pycache__/lsps.cpython-310.pyc
glclient/__pycache__/lsps.cpython-312.pyc
glclient/__pycache__/pairing.cpython-310.pyc
glclient/__pycache__/pairing.cpython-312.pyc
glclient/__pycache__/scheduler_pb2.cpython-310.pyc
glclient/__pycache__/scheduler_pb2.cpython-312.pyc
glclient/__pycache__/scheduler_pb2_grpc.cpython-312.pyc
glclient/__pycache__/tls.cpython-310.pyc
glclient/__pycache__/tls.cpython-312.pyc
glclient/glclient.abi3.so
glclient/glclient.pyi
glclient/greenlight.proto
glclient/greenlight_pb2.py
glclient/greenlight_pb2.pyi
glclient/greenlight_pb2_grpc.py
glclient/greenlight_pb2_grpc.pyi
glclient/lsps.py
glclient/pairing.py
glclient/py.typed
glclient/rpc.py
glclient/scheduler.proto
glclient/scheduler_pb2.py
glclient/scheduler_pb2.pyi
glclient/scheduler_pb2_grpc.py
glclient/scheduler_pb2_grpc.pyi
glclient/tls.py
gl_client-0.3.4.dist-info/RECORD
