Metadata-Version: 2.4
Name: gl-client
Version: 0.3.4
Requires-Dist: protobuf>=4
Requires-Dist: pyln-grpc-proto>=0.1
Summary: 
Author: Christian Decker, The Greenlight Team
Author-email: Christian Decker <decker@blockstream.com>
License: MIT
Requires-Python: >=3.8
Project-URL: Source Code, https://github.com/Blockstream/greenlight
